rpaths.py
rpaths-1.0.0.dist-info/LICENSE
rpaths-1.0.0.dist-info/METADATA
rpaths-1.0.0.dist-info/WHEEL
rpaths-1.0.0.dist-info/top_level.txt
rpaths-1.0.0.dist-info/RECORD
