Metadata-Version: 2.1
Name: rpaths
Version: 1.0.0
Summary: Path manipulation library
Home-page: https://github.com/remram44/rpaths
Author: Remi Rampin
Author-email: remirampin@gmail.com
License: BSD
Keywords: path,file,filename,pattern,fnmatch
Platform: UNKNOWN
Classifier: Development Status :: 5 - Production/Stable
Classifier: Intended Audience :: Developers
Classifier: License :: OSI Approved :: BSD License
Classifier: Operating System :: Microsoft :: Windows
Classifier: Operating System :: POSIX
Classifier: Programming Language :: Python
Classifier: Programming Language :: Python :: 2
Classifier: Programming Language :: Python :: 3
Classifier: Topic :: System :: Filesystems
